mltrackflow/__init__.py
mltrackflow/cli.py
mltrackflow/comparator.py
mltrackflow/pipeline.py
mltrackflow/report_generator.py
mltrackflow/tracker.py
mltrackflow/utils.py
mltrackflow/visualizer.py
mltrackflow-0.1.2.dist-info/licenses/LICENSE
tests/__init__.py
tests/test_tracker.py
mltrackflow-0.1.2.dist-info/METADATA
mltrackflow-0.1.2.dist-info/WHEEL
mltrackflow-0.1.2.dist-info/entry_points.txt
mltrackflow-0.1.2.dist-info/top_level.txt
mltrackflow-0.1.2.dist-info/RECORD
