Metadata-Version: 2.4
Name: mltrackflow
Version: 0.1.2
Summary: Makine öğrenimi eğitim süreçlerini şeffaf ve izlenebilir hale getiren kapsamlı Python kütüphanesi
Home-page: https://github.com/yourusername/mltrackflow
Author: Your Name
Author-email: Your Name <your.email@example.com>
License: MIT
Project-URL: Homepage, https://github.com/yourusername/mltrackflow
Project-URL: Documentation, https://mltrackflow.readthedocs.io
Project-URL: Repository, https://github.com/yourusername/mltrackflow
Project-URL: Bug Tracker, https://github.com/yourusername/mltrackflow/issues
Keywords: machine learning,experiment tracking,mlops,data science
Classifier: Development Status :: 3 - Alpha
Classifier: Intended Audience :: Developers
Classifier: Intended Audience :: Science/Research
Classifier: Topic :: Scientific/Engineering :: Artificial Intelligence
Classifier: License :: OSI Approved :: MIT License
Classifier: Programming Language :: Python :: 3
Classifier: Programming Language :: Python :: 3.8
Classifier: Programming Language :: Python :: 3.9
Classifier: Programming Language :: Python :: 3.10
Classifier: Programming Language :: Python :: 3.11
Requires-Python: >=3.8
License-File: LICENSE
Requires-Dist: numpy>=1.20.0
Requires-Dist: pandas>=1.3.0
Requires-Dist: scikit-learn>=1.0.0
Requires-Dist: matplotlib>=3.4.0
Requires-Dist: seaborn>=0.11.0
Requires-Dist: plotly>=5.0.0
Requires-Dist: joblib>=1.0.0
Requires-Dist: pyyaml>=5.4.0
Requires-Dist: tqdm>=4.60.0
Requires-Dist: tabulate>=0.8.9
Provides-Extra: dev
Requires-Dist: pytest>=7.0.0; extra == "dev"
Requires-Dist: pytest-cov>=3.0.0; extra == "dev"
Requires-Dist: black>=22.0.0; extra == "dev"
Requires-Dist: flake8>=4.0.0; extra == "dev"
Requires-Dist: sphinx>=4.0.0; extra == "dev"
Requires-Dist: sphinx-rtd-theme>=1.0.0; extra == "dev"
Provides-Extra: advanced
Requires-Dist: mlflow>=2.0.0; extra == "advanced"
Requires-Dist: optuna>=3.0.0; extra == "advanced"
Requires-Dist: shap>=0.41.0; extra == "advanced"
Requires-Dist: yellowbrick>=1.4; extra == "advanced"
Dynamic: author
Dynamic: home-page
Dynamic: license-file
Dynamic: requires-python
